jupyter_pandas_gui-0.10.0.dist-info/licenses/LICENSE
pandas_GUI/__init__.py
pandas_GUI/custom_fit_models.py
pandas_GUI/fit_Pandas_GUI.py
pandas_GUI/new_pandas_column_GUI.py
pandas_GUI/plot_Pandas_GUI.py
pandas_GUI/utils.py
jupyter_pandas_gui-0.10.0.dist-info/METADATA
jupyter_pandas_gui-0.10.0.dist-info/WHEEL
jupyter_pandas_gui-0.10.0.dist-info/top_level.txt
jupyter_pandas_gui-0.10.0.dist-info/RECORD
