Metadata-Version: 2.4
Name: jupyter_Pandas_GUI
Version: 0.10.0
Summary: Pandas expression composers using Jupyter widgets.
Home-page: https://jupyterphysscilab.github.io/jupyter_Pandas_GUI/
Author: Jonathan Gutow
Author-email: gutow@uwosh.edu
License: GPL-3.0+
Keywords: fitting,data-analysis,plotting,learning to code
Classifier: Development Status :: 4 - Beta
Classifier: Intended Audience :: Developers
Classifier: Intended Audience :: Education
Classifier: License :: OSI Approved :: GNU General Public License v3 or later (GPLv3+)
Classifier: Programming Language :: Python :: 3
Classifier: Programming Language :: JavaScript
Classifier: Operating System :: OS Independent
License-File: LICENSE
Requires-Dist: jupyter>=1.0.0
Requires-Dist: jupyterlab>=4.4.3
Requires-Dist: pandas>=1.5.2
Requires-Dist: numpy>=1.23.0
Requires-Dist: anywidget
Requires-Dist: plotly>=6.0.0
Requires-Dist: kaleido
Requires-Dist: ipywidgets>=8.1.7
Requires-Dist: JPSLUtils>=0.7.0
Requires-Dist: lmfit>=1.1.0
Requires-Dist: round-using-error>=1.2.0
Requires-Dist: sympy>=1.13
Dynamic: author
Dynamic: author-email
Dynamic: classifier
Dynamic: description
Dynamic: description-content-type
Dynamic: home-page
Dynamic: keywords
Dynamic: license
Dynamic: license-file
Dynamic: requires-dist
Dynamic: summary
